{
	"cmake" : 
	{
		"generator" : 
		{
			"multiConfig" : false,
			"name" : "Ninja"
		},
		"paths" : 
		{
			"cmake" : "D:/MySoftWare/Microsoft Visual Studio/2022/Professional/Common7/IDE/CommonExtensions/Microsoft/CMake/CMake/bin/cmake.exe",
			"cpack" : "D:/MySoftWare/Microsoft Visual Studio/2022/Professional/Common7/IDE/CommonExtensions/Microsoft/CMake/CMake/bin/cpack.exe",
			"ctest" : "D:/MySoftWare/Microsoft Visual Studio/2022/Professional/Common7/IDE/CommonExtensions/Microsoft/CMake/CMake/bin/ctest.exe",
			"root" : "D:/MySoftWare/Microsoft Visual Studio/2022/Professional/Common7/IDE/CommonExtensions/Microsoft/CMake/CMake/share/cmake-3.22"
		},
		"version" : 
		{
			"isDirty" : false,
			"major" : 3,
			"minor" : 22,
			"patch" : 22040401,
			"string" : "3.22.22040401-MSVC_2",
			"suffix" : ""
		}
	},
	"objects" : 
	[
		{
			"jsonFile" : "codemodel-v2-0a393c51a7e445776105.json",
			"kind" : "codemodel",
			"version" : 
			{
				"major" : 2,
				"minor" : 3
			}
		},
		{
			"jsonFile" : "cache-v2-7ad9be5ad68a96243e61.json",
			"kind" : "cache",
			"version" : 
			{
				"major" : 2,
				"minor" : 0
			}
		},
		{
			"jsonFile" : "cmakeFiles-v1-617ce7779e079d670068.json",
			"kind" : "cmakeFiles",
			"version" : 
			{
				"major" : 1,
				"minor" : 0
			}
		},
		{
			"jsonFile" : "toolchains-v1-334c21f2690c734aa4eb.json",
			"kind" : "toolchains",
			"version" : 
			{
				"major" : 1,
				"minor" : 0
			}
		}
	],
	"reply" : 
	{
		"client-MicrosoftVS" : 
		{
			"query.json" : 
			{
				"requests" : 
				[
					{
						"kind" : "cache",
						"version" : 2
					},
					{
						"kind" : "cmakeFiles",
						"version" : 1
					},
					{
						"kind" : "codemodel",
						"version" : 2
					},
					{
						"kind" : "toolchains",
						"version" : 1
					}
				],
				"responses" : 
				[
					{
						"jsonFile" : "cache-v2-7ad9be5ad68a96243e61.json",
						"kind" : "cache",
						"version" : 
						{
							"major" : 2,
							"minor" : 0
						}
					},
					{
						"jsonFile" : "cmakeFiles-v1-617ce7779e079d670068.json",
						"kind" : "cmakeFiles",
						"version" : 
						{
							"major" : 1,
							"minor" : 0
						}
					},
					{
						"jsonFile" : "codemodel-v2-0a393c51a7e445776105.json",
						"kind" : "codemodel",
						"version" : 
						{
							"major" : 2,
							"minor" : 3
						}
					},
					{
						"jsonFile" : "toolchains-v1-334c21f2690c734aa4eb.json",
						"kind" : "toolchains",
						"version" : 
						{
							"major" : 1,
							"minor" : 0
						}
					}
				]
			}
		}
	}
}
